LICENSE
README.rst
setup.py
uvicorn_daemonite/__init__.py
uvicorn_daemonite.egg-info/PKG-INFO
uvicorn_daemonite.egg-info/SOURCES.txt
uvicorn_daemonite.egg-info/dependency_links.txt
uvicorn_daemonite.egg-info/requires.txt
uvicorn_daemonite.egg-info/top_level.txt